{"chunk_definitions":[{"row":57,"row_count":1,"visible":true,"expansion_state":0,"options":{"engine":"r","label":"unnamed-chunk-33","dev":"png"},"document_id":"90617D62","chunk_id":"c7fguobyzqsmk","chunk_label":"unnamed-chunk-1"},{"row":71,"row_count":1,"visible":true,"expansion_state":0,"options":{"engine":"r","label":"unnamed-chunk-34","dev":"png"},"document_id":"90617D62","chunk_id":"cvcgveuaw7jbl","chunk_label":"unnamed-chunk-2"},{"row":105,"row_count":1,"visible":true,"expansion_state":0,"options":{"engine":"r","label":"unnamed-chunk-35","dev":"png"},"document_id":"90617D62","chunk_id":"cc4t3y51con4o","chunk_label":"unnamed-chunk-3"},{"row":151,"row_count":1,"visible":true,"expansion_state":0,"options":{"engine":"r","label":"unnamed-chunk-36","dev":"png"},"document_id":"90617D62","chunk_id":"c4oo7gm6rvw0r","chunk_label":"unnamed-chunk-4"},{"row":172,"row_count":1,"visible":true,"expansion_state":0,"options":{"engine":"r","label":"unnamed-chunk-37","dev":"png"},"document_id":"90617D62","chunk_id":"ch0ex78kegc2s","chunk_label":"unnamed-chunk-5"},{"row":219,"row_count":1,"visible":true,"expansion_state":0,"options":{"engine":"r","label":"unnamed-chunk-40","dev":"png"},"document_id":"90617D62","chunk_id":"cevuihx503hb5","chunk_label":"unnamed-chunk-8"},{"row":235,"row_count":1,"visible":true,"expansion_state":0,"options":{"engine":"r","label":"unnamed-chunk-41","dev":"png"},"document_id":"90617D62","chunk_id":"cqp7jrmahda4l","chunk_label":"unnamed-chunk-9"},{"row":355,"row_count":1,"visible":true,"expansion_state":0,"options":{"engine":"r","label":"unnamed-chunk-45","dev":"png"},"document_id":"90617D62","chunk_id":"cn7jw91af4cbw","chunk_label":"unnamed-chunk-11"},{"row":254,"row_count":1,"visible":true,"expansion_state":0,"options":{"engine":"r","label":"unnamed-chunk-42","dev":"png"},"document_id":"90617D62","chunk_id":"c6eza8app03ae","chunk_label":"unnamed-chunk-10"},{"row":202,"row_count":1,"visible":true,"expansion_state":0,"options":{"engine":"r","label":"unnamed-chunk-39","dev":"png"},"document_id":"90617D62","chunk_id":"c1iamu0jcpow1","chunk_label":"unnamed-chunk-7"},{"row":189,"row_count":1,"visible":true,"expansion_state":0,"options":{"engine":"r","label":"unnamed-chunk-38","dev":"png"},"document_id":"90617D62","chunk_id":"c6j3l26wx1tr0","chunk_label":"unnamed-chunk-6"}],"doc_write_time":1732178837,"chunk_rendered_width":534}